sphinxcontrib/towncrier/__init__.py
sphinxcontrib/towncrier/_compat.py
sphinxcontrib/towncrier/_data_transformers.py
sphinxcontrib/towncrier/_fragment_discovery.py
sphinxcontrib/towncrier/_scm_version.py
sphinxcontrib/towncrier/_scm_version.pyi
sphinxcontrib/towncrier/_towncrier.py
sphinxcontrib/towncrier/_version.py
sphinxcontrib/towncrier/ext.py
sphinxcontrib/towncrier/py.typed
sphinxcontrib_towncrier-0.4.0a0.dist-info/LICENSE
sphinxcontrib_towncrier-0.4.0a0.dist-info/METADATA
sphinxcontrib_towncrier-0.4.0a0.dist-info/WHEEL
sphinxcontrib_towncrier-0.4.0a0.dist-info/top_level.txt
sphinxcontrib_towncrier-0.4.0a0.dist-info/zip-safe
sphinxcontrib_towncrier-0.4.0a0.dist-info/RECORD
